dearpygui/__init__.py
dearpygui/_dearpygui.pyi
dearpygui/_dearpygui.so
dearpygui/dearpygui.py
dearpygui/demo.py
dearpygui/experimental.py
dearpygui_nodezoomfork-2.1.1.dist-info/LICENSE
dearpygui_nodezoomfork-2.1.1.dist-info/METADATA
dearpygui_nodezoomfork-2.1.1.dist-info/WHEEL
dearpygui_nodezoomfork-2.1.1.dist-info/top_level.txt
dearpygui_nodezoomfork-2.1.1.dist-info/RECORD
